beyondpapers/__init__.py
beyondpapers/regressors/__base_regressor.py
beyondpapers/regressors/__init__.py
beyondpapers/regressors/__tensorflow_regressor.py
beyondpapers/switcher/__init__.py
beyondpapers/switcher/__switcher.py
beyondpapers-0.1.0.dist-info/LICENSE.md
beyondpapers-0.1.0.dist-info/METADATA
beyondpapers-0.1.0.dist-info/WHEEL
beyondpapers-0.1.0.dist-info/top_level.txt
beyondpapers-0.1.0.dist-info/RECORD
