Metadata-Version: 2.1
Name: beyondpapers
Version: 0.1.0
Summary: Collection Machine Learning algorithm beyond papers
Home-page: https://github.com/ai-beyondpapers/beyondpapers
Author: AI Beyond Papers
Author-email: aibeyondpaper@gmail.com
License: MIT License
Platform: UNKNOWN
License-File: LICENSE.md
Requires-Dist: numpy
Requires-Dist: pandas
Requires-Dist: tensorflow
Requires-Dist: scikit-learn
